Metadata-Version: 2.1
Name: tanks-wrld-art
Version: 1.0
Summary: Tanks Console Game
Home-page: UNKNOWN
Author-email: picurke@gmail.com
License: UNKNOWN
Platform: UNKNOWN
